pynormalizer/__init__.py
pynormalizer/core.py
pynormalizer-0.1.0.dist-info/METADATA
pynormalizer-0.1.0.dist-info/WHEEL
pynormalizer-0.1.0.dist-info/top_level.txt
pynormalizer-0.1.0.dist-info/RECORD
