Metadata-Version: 2.4
Name: pynormalizer
Version: 0.1.0
Summary: Unicode, whitespace, and accent normalization for multilingual text
Author: PyLib Contributors
License: MIT
Keywords: unicode,normalization,text,multilingual
Classifier: Development Status :: 3 - Alpha
Classifier: Intended Audience :: Developers
Classifier: License :: OSI Approved :: MIT License
Classifier: Programming Language :: Python :: 3
Requires-Python: >=3.8
